diarypy/__init__.py
diarypy/diary.py
diarypy/utils.py
diarypy/version.py
diarypy/tests/__init__.py
diarypy/tests/test_diary.py
diarypy-0.4.2.dist-info/LICENSE.txt
diarypy-0.4.2.dist-info/METADATA
diarypy-0.4.2.dist-info/WHEEL
diarypy-0.4.2.dist-info/top_level.txt
diarypy-0.4.2.dist-info/RECORD
