Metadata-Version: 2.1
Name: diarypy
Version: 0.4.2
Summary: Diary to create notebooks and store intermediate results and figures
Home-page: https://github.com/perellonieto/DiaryPy
Author: Miquel Perello Nieto
Author-email: perello.nieto@gmail.com
License: UNKNOWN
Download-URL: https://github.com/perellonieto/DiaryPy/archive/0.4.2.tar.gz
Keywords: diary,notebook,logging,figures,experiments
Platform: UNKNOWN
Classifier: Programming Language :: Python :: 3
Classifier: License :: OSI Approved :: MIT License
Classifier: Operating System :: OS Independent
Requires-Python: >=3.6
